deephonor_gym/__init__.py
deephonor_gym/core/DHGym.py
deephonor_gym/core/Free.cp39-win_amd64.pyd
deephonor_gym/dist/index.html
deephonor_gym/dist/assets/freeP-e.CjZXfFYQ.wasm
deephonor_gym/dist/assets/index-Dj2KqI3G.js
deephonor_gym/dist/assets/index.BRG-_uNh.css
deephonor_gym/dist/assets/logo.CAtq87-O.png
deephonor_gym/dist/assets/screenSpaceCurvature.fragment-BqvbNYDx.js
deephonor_gym/example/browser.ipynb
deephonor_gym/example/train.ipynb
deephonor_gym/example/models/ball.urdf
deephonor_gym/example/models/heightground.jpeg
deephonor_gym-0.1.3.dist-info/licenses/LICENSE
deephonor_gym-0.1.3.dist-info/METADATA
deephonor_gym-0.1.3.dist-info/WHEEL
deephonor_gym-0.1.3.dist-info/top_level.txt
deephonor_gym-0.1.3.dist-info/RECORD
