Metadata-Version: 2.4
Name: deephonor_gym
Version: 0.1.3
Summary: deephonor-gym physics simulator
Author: DingGuohua
Author-email: m17797618108@163.com
Classifier: Programming Language :: Python :: 3
Classifier: License :: OSI Approved :: GNU Affero General Public License v3
Classifier: Operating System :: OS Independent
License-File: LICENSE
Dynamic: author
Dynamic: author-email
Dynamic: classifier
Dynamic: description
Dynamic: description-content-type
Dynamic: license-file
Dynamic: summary
